odoo8_addon_account_invoice_import_ubl-8.0.1.0.0.99.dev14-nspkg.pth
odoo_addons/account_invoice_import_ubl/README.rst
odoo_addons/account_invoice_import_ubl/__init__.py
odoo_addons/account_invoice_import_ubl/__openerp__.py
odoo_addons/account_invoice_import_ubl/demo/demo_data.xml
odoo_addons/account_invoice_import_ubl/i18n/account_invoice_import_ubl.pot
odoo_addons/account_invoice_import_ubl/i18n/fr.po
odoo_addons/account_invoice_import_ubl/i18n/sl.po
odoo_addons/account_invoice_import_ubl/static/description/icon.png
odoo_addons/account_invoice_import_ubl/tests/__init__.py
odoo_addons/account_invoice_import_ubl/tests/test_ubl.py
odoo_addons/account_invoice_import_ubl/tests/files/UBLKetentest_Referentiefactuur_20150100.xml
odoo_addons/account_invoice_import_ubl/tests/files/efff_BE0505890632_160421_Inv_16117778.xml
odoo_addons/account_invoice_import_ubl/wizard/__init__.py
odoo_addons/account_invoice_import_ubl/wizard/account_invoice_import.py
odoo8_addon_account_invoice_import_ubl-8.0.1.0.0.99.dev14.dist-info/METADATA
odoo8_addon_account_invoice_import_ubl-8.0.1.0.0.99.dev14.dist-info/WHEEL
odoo8_addon_account_invoice_import_ubl-8.0.1.0.0.99.dev14.dist-info/namespace_packages.txt
odoo8_addon_account_invoice_import_ubl-8.0.1.0.0.99.dev14.dist-info/top_level.txt
odoo8_addon_account_invoice_import_ubl-8.0.1.0.0.99.dev14.dist-info/RECORD
